{
  "人文探究": ["研究者", "学芸員", "編集者", "ライター"],
  "言語表現": ["翻訳家", "通訳者", "国際広報", "語学教師"],
  "文化批評": ["ジャーナリスト", "評論家", "メディアプロデューサー"],
  "社会分析": ["コンサルタント", "マーケティングリサーチャー", "政策アナリスト"],
  "政治法制度": ["弁護士", "行政書士", "国家・地方公務員"],
  "経済ビジネス": ["経営企画", "ファイナンシャルプランナー", "起業家"],
  "環境科学": ["環境コンサルタント", "サステナビリティ担当", "再生可能エネルギー技術者"],
  "地球惑星": ["地質学者", "気象予報士", "宇宙開発技術者"],
  "物理数理": ["データサイエンティスト", "クオンツアナリスト", "理論物理学者"],
  "化学材料": ["素材メーカー研究開発", "化学プラント技術者", "化粧品開発"],
  "生命医科学": ["医師", "製薬会社研究職", "臨床開発モニター"],
  "農環境": ["農業技術者", "食品メーカー開発職", "スマート農業コンサルタント"],
  "情報科学": ["ソフトウェアエンジニア", "AIエンジニア", "セキュリティ専門家"],
  "デジタル創造": ["UI/UXデザイナー", "ゲームクリエイター", "メディアアーティスト"],
  "芸術実践": ["アーティスト", "デザイナー", "舞台演出家"],
  "教育革新": ["教育コンテンツ開発", "EdTechプランナー", "スクールカウンセラー"],
  "スポーツ科学": ["スポーツトレーナー", "スポーツデータアナリスト", "健康運動指導士"],
  "デザイン思考": ["サービスデザイナー", "UXリサーチャー", "プロダクトマネージャー"]
}
